cas.py
python_cas-1.5.0.dist-info/LICENSE.txt
python_cas-1.5.0.dist-info/METADATA
python_cas-1.5.0.dist-info/WHEEL
python_cas-1.5.0.dist-info/top_level.txt
python_cas-1.5.0.dist-info/RECORD
